pytortilla/__init__.py
pytortilla/create/__init__.py
pytortilla/create/main.py
pytortilla/create/utils.py
pytortilla/datamodel/__init__.py
pytortilla/datamodel/data/rai_admin0.parquet
pytortilla/datamodel/data/rai_admin1.parquet
pytortilla/datamodel/data/rai_admin2.parquet
pytortilla/datamodel/main.py
pytortilla/datamodel/utils.py
pytortilla-0.5.1.dist-info/LICENSE
pytortilla-0.5.1.dist-info/METADATA
pytortilla-0.5.1.dist-info/WHEEL
pytortilla-0.5.1.dist-info/RECORD
