Metadata-Version: 2.1
Name: pytortilla
Version: 0.5.1
Summary: The file format behind TACO.
Home-page: https://github.com/tacofoundation/tortilla-python
Author: Cesar Aybar
Author-email: fcesar.aybar@uv.es
Requires-Python: >=3.9,<4.0
Classifier: Programming Language :: Python :: 3
Classifier: Programming Language :: Python :: 3.9
Classifier: Programming Language :: Python :: 3.10
Classifier: Programming Language :: Python :: 3.11
Classifier: Programming Language :: Python :: 3.12
Requires-Dist: geopandas (>=1.0.1)
Requires-Dist: pandas (>=2.1.4)
Requires-Dist: pyarrow (>=17.0.0)
Requires-Dist: pydantic (>=2.10.3)
Requires-Dist: requests (>=2.32.3)
Requires-Dist: tqdm (>=4.66.5)
Project-URL: Documentation, https://tacofoundation.github.io/tortilla-python
Project-URL: Repository, https://github.com/tacofoundation/tortilla-python
